README.md
setup.cfg
setup.py
PyCoShREM.egg-info/PKG-INFO
PyCoShREM.egg-info/SOURCES.txt
PyCoShREM.egg-info/dependency_links.txt
PyCoShREM.egg-info/requires.txt
PyCoShREM.egg-info/top_level.txt
coshrem/__init__.py
coshrem/shearlet.py
coshrem/shearletsystem.py
coshrem/util/__init__.py
coshrem/util/cone.py
coshrem/util/curvature.py
coshrem/util/image.py