Metadata-Version: 1.1
Name: PyCoShREM
Version: 0.0.2
Summary: Complex shearlet based edge and ridge measurement
Home-page: http://www.math.uni-bremen.de/cda/software.html
Author: RG Computational Data Analysis, University Bremen: Rafael Reisenhofer, Jonas Wloka
Author-email: reisenhofer@math.uni-bremen.de
License: UNKNOWN
Download-URL: https://github.com/rgcda/pycoshrem/archive/0.0.2.tar.gz
Keywords: image-processing shearlet edge ridge
Platform: UNKNOWN
Classifier: Development Status :: 3 - Alpha
Classifier: Intended Audience :: Developers
Classifier: Topic :: Scientific/Engineering :: Image Recognition
Classifier: Programming Language :: Python :: 3.5
